[
  {
    "id":1,"name":"Basmati Biryani Rice, 5kg",
    "description":"Basmati Biryani Rice, 5kg",
    "product_category_id":3,
    "price":"4.49",
    "cs_sku":"184578784-6",
    "image_front":"http://lorempixel.com/100/130/food/",
    "qty":293
  },
  {
    "id":2,
    "name":"Cheese Whiz Sandwich Spread, 150g",
    "description":"Cheese Whiz Sandwich Spread, 150g",
    "product_category_id":8,
    "price":"4.67",
    "cs_sku":"620802438-2",
    "image_front":"http://lorempixel.com/100/130/food/",
    "qty":273
  },
  {
    "id":3,
    "name":"Mrs. Fields Chocolate Chip Cookies, 5pcs",
    "description":"Mrs. Fields Chocolate Chip Cookies, 5pcs",
    "product_category_id":7,
    "price":"5.98",
    "cs_sku":"793013921-2",
    "image_front":"http://lorempixel.com/100/130/food/",
    "qty":411
  },
  {
    "id":4,
    "name":"Fox Dark Chocolate Cookies, 5pcs",
    "description":"Fox Dark Chocolate Cookies, 5pcs",
    "product_category_id":7,
    "price":"6.59",
    "cs_sku":"962373977-X",
    "image_front":"http://lorempixel.com/100/130/food/",
    "qty":274
  },
  {
    "id":5,
    "name":"Thai Fragrant Rice, 5kg",
    "description":"Thai Fragrant Rice, 5kg",
    "product_category_id":2,
    "price":"5.20",
    "cs_sku":"494098700-0",
    "image_front":"http://lorempixel.com/100/130/food/",
    "qty":493
  },
  {
    "id":6,
    "name":"Lady's Choice Tuna Spread, 200g",
    "description":"Lady's Choice Tuna Spread",
    "product_category_id":8,
    "price":"4.36",
    "cs_sku":"360968466-6",
    "image_front":"http://lorempixel.com/100/130/food/",
    "qty":213
  },
  {
    "id":7,
    "name":"Indian Basmati Rice, 5kg",
    "description":"Indian Basmati Rice, 5kg",
    "product_category_id":3,
    "price":"5.40",
    "cs_sku":"538556366-8",
    "image_front":"http://lorempixel.com/100/130/food/",
    "qty":353
  },
  {
    "id":8,
    "name":"Thai White Rice, 5kg",
    "description":"Thai White Rice, 5kg",
    "product_category_id":2,
    "price":"6.02",
    "cs_sku":"158246186-4",
    "image_front":"http://lorempixel.com/100/130/food/",
    "qty":457
  },
  {
    "id":9,
    "name":"Lady's Choice Ham Spread, 200g",
    "description":"Lady's Choice Ham Spread, 200g",
    "product_category_id":8,
    "price":"2.63",
    "cs_sku":"036000046-0",
    "image_front":"http://lorempixel.com/100/130/food/",
    "qty":446
  },
  {
    "id":10,
    "name":"Gardenia Wheat Bread Loaf, 200g",
    "description":"Gardenia Wheat Bread Loaf, 200g",
    "product_category_id":6,
    "price":"1.70",
    "cs_sku":"640956999-8",
    "image_front":"http://lorempixel.com/100/130/food/",
    "qty":435
  },

  {
    "id":11,
    "name":"Hunt's Pork and Beans, 200g",
    "description":"Hunt's Pork and Beans, 200g",
    "product_category_id":10,
    "price":"1.70",
    "cs_sku":"640956999-9",
    "image_front":"http://lorempixel.com/100/130/food/",
    "qty":435
  }
]